<?xml version="1.0" encoding="utf-8"?>
<LanguageData>
	<!-- ================================ Cortical Stack Hediff	====================== -->
	<VFEU_CorticalStack.label>皮質堆疊</VFEU_CorticalStack.label>
	<VFEU_CorticalStack.labelNoun>一個皮質堆疊</VFEU_CorticalStack.labelNoun>
	<VFEU_CorticalStack.description>一個已安裝的皮質堆疊。</VFEU_CorticalStack.description>

	<!-- ================================ Sleeve Base ====================== -->
	<VFEU_EmptySleeve.label>空白義體</VFEU_EmptySleeve.label>
	<VFEU_EmptySleeve.description>一個空白義體。</VFEU_EmptySleeve.description>
	<VFEU_EmptySleeve.stages.empty.label>空白</VFEU_EmptySleeve.0.label>

	<!-- ================================ Sleeve Shock Hediff ====================== -->
	<VFEU_SleeveShock.label>義體休克</VFEU_SleeveShock.label>
	<VFEU_SleeveShock.description>由於轉換身體而處於休克狀態。</VFEU_SleeveShock.description>
	<VFEU_SleeveShock.stages.wearing_off.label>磨損</VFEU_SleeveShock.0.label>
	<VFEU_SleeveShock.stages.irritated.label>發炎</VFEU_SleeveShock.1.label>

	<!-- ================================ Sleeve Qualitys ====================== -->
	<VFEU_Sleeve_Quality_Awful.label>糟糕品質的義體</VFEU_Sleeve_Quality_Awful.label>
	<VFEU_Sleeve_Quality_Poor.label>低劣品質的義體</VFEU_Sleeve_Quality_Poor.label>
	<VFEU_Sleeve_Quality_Normal.label>普通品質的義體</VFEU_Sleeve_Quality_Normal.label>
	<VFEU_Sleeve_Quality_Good.label>不錯品質的義體</VFEU_Sleeve_Quality_Good.label>
	<VFEU_Sleeve_Quality_Excellent.label>優良品質的義體</VFEU_Sleeve_Quality_Excellent.label>
	<VFEU_Sleeve_Quality_Masterwork.label>大師品質的義體</VFEU_Sleeve_Quality_Masterwork.label>
	<VFEU_Sleeve_Quality_Legendary.label>傳奇品質的義體</VFEU_Sleeve_Quality_Legendary.label>
</LanguageData>